{
  "name": "regional",
  "age": 29,
  "occupation": "artist",
  "personality": {
    "type": "creative",
    "humor_style": "silly",
    "social_preference": "lone wolf"
  },
  "interests": {
    "primary_interests": [
      "sports",
      "technology"
    ],
    "secondary_interests": [
      "reading",
      "traveling",
      "gaming"
    ],
    "preferred_topics": [
      "science fiction"
    ],
    "disliked_topics": [
      "economics",
      "politics"
    ]
  },
  "background": {
    "hometown": "Tokyo",
    "education_level": "advanced",
    "values": [
      "individuality"
    ]
  },
  "communication_style": {
    "favorite_words": [
      "amazing",
      "fascinating",
      "cool"
    ],
    "formality_level": "semi-formal",
    "conversation_tendency": "balanced"
  },
  "social_connections": {
    "groups": [
      "Art Collective",
      "Nature Lovers",
      "Book Club"
    ],
    "friendliness_rating": "selectively friendly"
  }
}